tree_decode
